virtual_warehouse/__init__.py
virtual_warehouse/__main__.py
virtual_warehouse/app.py
virtual_warehouse/data/__init__.py
virtual_warehouse/data/agent_parser.py
virtual_warehouse/data/data_model.py
virtual_warehouse/data/excel_parser.py
virtual_warehouse/data/onto_manager.py
virtual_warehouse/data/utils.py
virtual_warehouse/environment.py
virtual_warehouse/location_models.py
virtual_warehouse/location_utils.py
virtual_warehouse/main.qrc
virtual_warehouse/main_rc.py
virtual_warehouse/map.py
virtual_warehouse/plugin.py
virtual_warehouse/plugins/__init__.py
virtual_warehouse/plugins/item_frequencies.py
virtual_warehouse/plugins/order_frequencies.py
virtual_warehouse/qtquickcontrols2.conf
virtual_warehouse/resources/images/close_icon.png
virtual_warehouse/resources/images/dimension_icon.png
virtual_warehouse/resources/images/histogram_icon.png
virtual_warehouse/resources/images/icon.ico
virtual_warehouse/resources/images/icon.png
virtual_warehouse/resources/images/max_weight_icon.png
virtual_warehouse/resources/images/menu_icon.png
virtual_warehouse/resources/images/search_icon.png
virtual_warehouse/resources/images/textures/blue.png
virtual_warehouse/resources/images/textures/default.png
virtual_warehouse/resources/images/textures/red.png
virtual_warehouse/resources/js/utils.js
virtual_warehouse/resources/objects/floor.mtl
virtual_warehouse/resources/objects/floor.obj
virtual_warehouse/resources/objects/oilrig.obj
virtual_warehouse/resources/objects/rack.mtl
virtual_warehouse/resources/objects/rack.obj
virtual_warehouse/resources/qml/AgentView.qml
virtual_warehouse/resources/qml/AgentVisualizer.qml
virtual_warehouse/resources/qml/ClassView.qml
virtual_warehouse/resources/qml/ConnectionsMenu.qml
virtual_warehouse/resources/qml/CustomItem.qml
virtual_warehouse/resources/qml/Dialogs.qml
virtual_warehouse/resources/qml/FilterMenu.qml
virtual_warehouse/resources/qml/ItemListView.qml
virtual_warehouse/resources/qml/LoadingOverlay.qml
virtual_warehouse-0.2.1.dist-info/entry_points.txt
virtual_warehouse-0.2.1.dist-info/LICENSE
virtual_warehouse-0.2.1.dist-info/WHEEL
virtual_warehouse-0.2.1.dist-info/METADATA
virtual_warehouse-0.2.1.dist-info/RECORD
