Metadata-Version: 2.1
Name: virtual-warehouse
Version: 0.2.1
Summary: Warehouse visualisation app
Home-page: https://github.com/Breta01/virtual-warehouse
Keywords: visualization,warehouse
Author: Břetislav Hájek
Author-email: info@bretahajek.com
Requires-Python: >=3.6,<3.9
Classifier: Programming Language :: Python :: 3
Classifier: Programming Language :: Python :: 3.6
Classifier: Programming Language :: Python :: 3.7
Classifier: Programming Language :: Python :: 3.8
Requires-Dist: Owlready2 (==0.30)
Requires-Dist: PySide2 (==5.15.0)
Requires-Dist: python-xlsxio (>=0.1.3,<0.2.0)
Requires-Dist: rdflib (>=5.0.0,<6.0.0)
Requires-Dist: requests (>=2.25.1,<3.0.0)
Requires-Dist: xlrd (==2.0.1)
Project-URL: Documentation, https://virtual-warehouse.readthedocs.io
Project-URL: Repository, https://github.com/Breta01/virtual-warehouse
